powerlingapi/File.py
powerlingapi/Form.py
powerlingapi/Order.py
powerlingapi/__init__.py
powerlingapi/powerlingapi.py
powerlingapi/exceptions/__init__.py
powerlingapi/exceptions/api.py
powerlingapi/exceptions/file.py
powerlingapi/exceptions/form.py
powerlingapi/exceptions/order.py
powerling_api_sdk-0.1.7.dist-info/LICENSE
powerling_api_sdk-0.1.7.dist-info/METADATA
powerling_api_sdk-0.1.7.dist-info/WHEEL
powerling_api_sdk-0.1.7.dist-info/top_level.txt
powerling_api_sdk-0.1.7.dist-info/RECORD
