Metadata-Version: 2.1
Name: powerling-api-sdk
Version: 0.1.7
Summary: SDK for Powerling API
Author: Powerling
Author-email: contact@powerling.com
Classifier: Development Status :: 3 - Alpha
Classifier: Intended Audience :: Developers
Classifier: License :: OSI Approved :: GNU General Public License v3 or later (GPLv3+)
Classifier: Programming Language :: Python :: 3
Classifier: Operating System :: OS Independent
Classifier: Operating System :: Microsoft :: Windows
Classifier: Operating System :: MacOS :: MacOS X
Classifier: Operating System :: POSIX
Requires-Python: >=3.6
License-File: LICENSE
Requires-Dist: requests
